{
    "Mississippi":5,
    "Oklahoma":9,
    "Delaware":38,
    "Minnesota":39,
    "Illinois":65,
    "Arkansas":11,
    "New Mexico":10,
    "Ohio":15,
    "Indiana":11,
    "Maryland":63,
    "Louisiana":12,
    "Texas":20,
    "Wyoming":6,
    "Tennessee":24,
    "Arizona":8,
    "Wisconsin":24,
    "Michigan":20,
    "Kansas":8,
    "Utah":11,
    "Virginia":12,
    "Oregon":24,
    "Connecticut":85,
    "Montana":4,
    "California":100,
    "Idaho":5,
    "West Virginia":24,
    "South Carolina":12,
    "New Hampshire":10,
    "Massachusetts":101,
    "Vermont":3,
    "Georgia":6,
    "North Dakota":14,
    "Pennsylvania":37,
    "Florida":21,
    "Alaska":3,
    "Kentucky":7,
    "Hawaii":78,
    "Nebraska":22,
    "Missouri":8,
    "Iowa":25,
    "Alabama":10,
    "Rhode Island":43,
    "South Dakota":5,
    "Colorado":30,
    "New Jersey":67,
    "Washington":41,
    "North Carolina":30,
    "New York":76,
    "Nevada":11,
    "Maine":11
}